manuscripts/__init__.py
manuscripts/_version.py
manuscripts/config.py
manuscripts/esquery.py
manuscripts/report.py
manuscripts/latex_template/activity.tex
manuscripts/latex_template/community.tex
manuscripts/latex_template/logo-eps-converted-to.pdf
manuscripts/latex_template/logo.eps
manuscripts/latex_template/makefile
manuscripts/latex_template/overview.tex
manuscripts/latex_template/process.tex
manuscripts/latex_template/report.tex
manuscripts/latex_template/activity/gerrit.tex
manuscripts/latex_template/activity/git.tex
manuscripts/latex_template/activity/github.tex
manuscripts/latex_template/activity/mls.tex
manuscripts/latex_template/community/git.tex
manuscripts/latex_template/community/mls.tex
manuscripts/latex_template/overview/efficiency-gerrit.tex
manuscripts/latex_template/overview/efficiency-github.tex
manuscripts/latex_template/overview/summary.tex
manuscripts/latex_template/process/gerrit.tex
manuscripts/latex_template/process/github_prs.tex
manuscripts/metrics/__init__.py
manuscripts/metrics/gerrit.py
manuscripts/metrics/git.py
manuscripts/metrics/github_issues.py
manuscripts/metrics/github_prs.py
manuscripts/metrics/its.py
manuscripts/metrics/jira.py
manuscripts/metrics/metrics.py
manuscripts/metrics/mls.py
manuscripts/metrics/stackexchange.py
manuscripts-0.2.20.data/scripts/manuscripts
manuscripts-0.2.20.data/scripts/manuscripts2
manuscripts2/__init__.py
manuscripts2/elasticsearch.py
manuscripts2/report.py
manuscripts2/utils.py
manuscripts2/latex_template/activity.tex
manuscripts2/latex_template/community.tex
manuscripts2/latex_template/logo-eps-converted-to.pdf
manuscripts2/latex_template/logo.eps
manuscripts2/latex_template/makefile
manuscripts2/latex_template/overview.tex
manuscripts2/latex_template/process.tex
manuscripts2/latex_template/report.tex
manuscripts2/latex_template/activity/gerrit.tex
manuscripts2/latex_template/activity/git.tex
manuscripts2/latex_template/activity/mls.tex
manuscripts2/latex_template/community/git.tex
manuscripts-0.2.20.dist-info/LICENSE
manuscripts-0.2.20.dist-info/METADATA
manuscripts-0.2.20.dist-info/WHEEL
manuscripts-0.2.20.dist-info/top_level.txt
manuscripts-0.2.20.dist-info/RECORD
