Metadata-Version: 2.1
Name: manuscripts
Version: 0.2.20
Summary: Produce reports based on GrimoireLab data
Home-page: https://github.com/chaoss/grimoirelab-manuscripts
Author: Bitergia
Author-email: grimoirelab-discussions@lists.linuxfoundation.org
License: GPLv3
Keywords: development repositories analytics
Platform: UNKNOWN
Classifier: Development Status :: 5 - Production/Stable
Classifier: Intended Audience :: Developers
Classifier: Topic :: Software Development
Classifier: License :: OSI Approved :: GNU General Public License v3 or later (GPLv3+)
Classifier: Programming Language :: Python :: 3
Requires-Dist: matplotlib
Requires-Dist: prettyplotlib
Requires-Dist: elasticsearch-dsl
Requires-Dist: grimoire-elk (>=0.30.4)
Requires-Dist: sortinghat (>=0.4.2)
